cytoskel/__init__.py
cytoskel/cli.py
cytoskel/s3_access_grants.py
cytoskel/stacks/README.md
cytoskel/stacks/__init__.py
cytoskel/stacks/staging_cpg.py
cytoskel/utils.py
cytoskel-0.2.0.dist-info/METADATA
cytoskel-0.2.0.dist-info/WHEEL
cytoskel-0.2.0.dist-info/entry_points.txt
cytoskel-0.2.0.dist-info/RECORD
