Metadata-Version: 2.1
Name: cytoskel
Version: 0.2.0
Summary: 
Author: Ankur Kumar
Author-email: ank@leoank.me
Requires-Python: >=3.10,<4.0
Classifier: Programming Language :: Python :: 3
Classifier: Programming Language :: Python :: 3.10
Classifier: Programming Language :: Python :: 3.11
Classifier: Programming Language :: Python :: 3.12
Requires-Dist: boto3 (>=1.34,<2.0)
Requires-Dist: click (>=8.1,<9.0)
Requires-Dist: pulumi (>=3.111,<4.0)
Requires-Dist: pulumi-aws (>=6.27,<7.0)
